python_zebedee_sdk/__init__.py
python_zebedee_sdk/client.py
python_zebedee_sdk/config.py
python_zebedee_sdk/Response/__init__.py
python_zebedee_sdk/Response/authorization/__init__.py
python_zebedee_sdk/Response/authorization/wallet.py
python_zebedee_sdk/Response/charge/__init__.py
python_zebedee_sdk/Response/charge/create_charge.py
python_zebedee_sdk/Response/charge/decode_charge.py
python_zebedee_sdk/Response/charge/get_charge.py
python_zebedee_sdk/Response/email/__init__.py
python_zebedee_sdk/Response/email/send_payment.py
python_zebedee_sdk/Response/gamertag/__init__.py
python_zebedee_sdk/Response/gamertag/charges.py
python_zebedee_sdk/Response/gamertag/get_gamertag.py
python_zebedee_sdk/Response/gamertag/get_id.py
python_zebedee_sdk/Response/gamertag/send_payment.py
python_zebedee_sdk/Response/gamertag/transaction.py
python_zebedee_sdk/Response/lightning/__init__.py
python_zebedee_sdk/Response/lightning/create_charge.py
python_zebedee_sdk/Response/lightning/send_payment.py
python_zebedee_sdk/Response/lightning/validate.py
python_zebedee_sdk/Response/payments/__init__.py
python_zebedee_sdk/Response/payments/get_payment.py
python_zebedee_sdk/Response/payments/send_payment.py
python_zebedee_sdk/Response/static/__init__.py
python_zebedee_sdk/Response/static/create_static_charges.py
python_zebedee_sdk/Response/static/get_static_charge.py
python_zebedee_sdk/Response/static/update_static_charge.py
python_zebedee_sdk/Response/voucher/__init__.py
python_zebedee_sdk/Response/voucher/create_voucher.py
python_zebedee_sdk/Response/voucher/get_voucher.py
python_zebedee_sdk/Response/voucher/redeem_voucher.py
python_zebedee_sdk/Response/voucher/revoke_voucher.py
python_zebedee_sdk/Response/wallet/__init__.py
python_zebedee_sdk/Response/withdrawal/__init__.py
python_zebedee_sdk/Response/withdrawal/create_withdrawal.py
python_zebedee_sdk/Response/withdrawal/get_withdrawal.py
python_zebedee_sdk/utils.py
python_zebedee_sdk-0.0.2.dist-info/LICENSE
python_zebedee_sdk-0.0.2.dist-info/METADATA
python_zebedee_sdk-0.0.2.dist-info/WHEEL
python_zebedee_sdk-0.0.2.dist-info/RECORD
